cmdl/__init__.py
cmdl/__main__.py
cmdl/_command_line_parser.py
cmdl/_exceptions.py
cmdl-0.1.1.dist-info/WHEEL
cmdl-0.1.1.dist-info/METADATA
cmdl-0.1.1.dist-info/RECORD
