Metadata-Version: 2.1
Name: cmdl
Version: 0.1.1
Summary: Simple command-line parser written in Python.
Author: Cypheriel
Author-email: cypheriel@github.com
Requires-Python: >=3.7,<4.0
Classifier: Programming Language :: Python :: 3
Classifier: Programming Language :: Python :: 3.7
Classifier: Programming Language :: Python :: 3.8
Classifier: Programming Language :: Python :: 3.9
Classifier: Programming Language :: Python :: 3.10
